agentloop/__init__.py
agentloop/input.py
agentloop/loop.py
agentloop-0.2.2.dist-info/LICENSE
agentloop-0.2.2.dist-info/METADATA
agentloop-0.2.2.dist-info/WHEEL
agentloop-0.2.2.dist-info/top_level.txt
agentloop-0.2.2.dist-info/RECORD
